pgtrio/__init__.py
pgtrio/_codecs.py
pgtrio/_connection.py
pgtrio/_cursor.py
pgtrio/_exceptions.py
pgtrio/_pgmsg.py
pgtrio/_pool.py
pgtrio/_prepared_stmt.py
pgtrio/_text_array.py
pgtrio/_transaction.py
pgtrio/_utils.py
pgtrio/_version.py
pgtrio-0.5.3.dist-info/LICENSE
pgtrio-0.5.3.dist-info/METADATA
pgtrio-0.5.3.dist-info/WHEEL
pgtrio-0.5.3.dist-info/top_level.txt
pgtrio-0.5.3.dist-info/RECORD
