Metadata-Version: 2.1
Name: pgtrio
Version: 0.5.3
Summary: A Trio-Native PostgreSQL Interface Library
Home-page: http://github.com/elektito/pgtrio
Author: Mostafa Razavi
Author-email: mostafa@sepent.com
License: MIT
Platform: UNKNOWN
Classifier: Programming Language :: Python :: 3
Classifier: License :: OSI Approved :: MIT License
Classifier: Operating System :: OS Independent
Requires-Dist: orjson (==3.6.8)
Requires-Dist: parsimonious (==0.9.0)
Requires-Dist: python-dateutil (==2.8.2)
Requires-Dist: trio (==0.20.0)
Provides-Extra: dev
Requires-Dist: coverage-badge (==1.1.0) ; extra == 'dev'
Requires-Dist: coverage (==6.3.2) ; extra == 'dev'
Requires-Dist: pytest-trio (==0.7.0) ; extra == 'dev'
Requires-Dist: pytest (==7.1.1) ; extra == 'dev'
Requires-Dist: twine (==4.0.0) ; extra == 'dev'
Requires-Dist: wheel ; extra == 'dev'
Provides-Extra: test
Requires-Dist: coverage-badge (==1.1.0) ; extra == 'test'
Requires-Dist: coverage (==6.3.2) ; extra == 'test'
Requires-Dist: pytest-trio (==0.7.0) ; extra == 'test'
Requires-Dist: pytest (==7.1.1) ; extra == 'test'
